{
  "iteration": 9,
  "timestamp": "2025-11-07T04:03:24Z",
  "source_tenant": "3cd87a41-1f61-4aef-a212-cefdecd9a2d1",
  "target_tenant": "c7674d41-af6c-46f5-89a5-d41495d2151e",
  "neo4j_resources": 2231,
  "resources_generated": 2384,
  "import_blocks": 152,
  "terraform_operations": {
    "planned": 1198,
    "successful": 215,
    "imports": 152,
    "creates": 63,
    "destroys": 0
  },
  "resources_deployed": 750,
  "resources_added": 3,
  "errors": 63,
  "already_exists_errors": 313,
  "bug_fixes_active": ["ConflictDetector_credentials", "ResourceExistenceValidator_6_apis"],
  "commit": "141a9c6",
  "status": "complete_with_errors",
  "notes": "Import strategy limitation - only checks RGs not individual resources. AlreadyExists reduced 92% for RGs but individual resources still problematic."
}
